{
  "generated_at": "2026-06-26T17:51:53.798Z",
  "stats_last_scraped_at": "2026-06-12T16:15:34.740Z",
  "stats_through_date": "2026-06-11",
  "scraped_game_count": 40,
  "season": 2026,
  "team": "The Big Papi's",
  "team_rating": {
    "team": "The Big Papi's",
    "team_id": "the_big_papi_s",
    "roster_size": "15",
    "active_players": "15",
    "matched_players": "15",
    "unmatched_players": "0",
    "projected_runs": "10.4203",
    "offense_index": "0.5307328816402559",
    "offense_rating": "0.16945875400520752",
    "defense_rating": "0",
    "overall_rating": "0.16945875400520752"
  },
  "human_summary": {
    "team_rank": 9,
    "total_teams": 12,
    "team_tier": "Middle-of-the-pack team",
    "expected_runs": 10.4203,
    "roster_size": 15,
    "active_players": 15,
    "matched_players": 15,
    "unmatched_players": 0,
    "roster_match_rate": 1,
    "strongest_absence": {
      "player_name": "Ralph Avallone",
      "run_swing": 1.49,
      "win_probability_swing": 0.0801
    },
    "easiest_absence": {
      "player_name": "Temple Houston",
      "run_swing": 0,
      "win_probability_swing": 0
    },
    "plain_english_notes": [
      "The Big Papi's projects as the 9th-strongest team out of 12.",
      "The model expects about 10.4 runs per game with the current full roster.",
      "15 of 15 players have a historical match in the dataset.",
      "Every roster spot matched to a historical player record."
    ]
  },
  "hit_direction_profile": {
    "weighted_h2l": 714.3,
    "weighted_h2c": 904.7,
    "weighted_h2r": 97.5,
    "weighted_total": 1716.5,
    "h2l_percentage": 0.41613748907660936,
    "h2c_percentage": 0.527060879697058,
    "h2r_percentage": 0.05680163122633265,
    "players_with_direction_data": 15,
    "matched_roster_players": 15,
    "seasons_used": [
      "2023",
      "2024",
      "2025"
    ],
    "weighting_note": "Uses the last three seasons before the report year with weights of 1.0 for the previous year, 0.9 for two years back, and 0.8 for three years back. Seasons with blank H2L/H2C/H2R data are skipped."
  },
  "player_direction_stats": [
    {
      "player_name": "RJ Leonard",
      "h2l_percentage": 0.6231647634584013,
      "h2c_percentage": 0.3681348558999456,
      "h2r_percentage": 0.008700380641653073,
      "weighted_left": 114.60000000000001,
      "weighted_center": 67.7,
      "weighted_right": 1.6,
      "weighted_total": 183.9,
      "seasons_used": [
        "2023",
        "2024",
        "2025"
      ]
    },
    {
      "player_name": "Mark Armelino",
      "h2l_percentage": 0.5002724795640328,
      "h2c_percentage": 0.47956403269754766,
      "h2r_percentage": 0.020163487738419618,
      "weighted_left": 91.80000000000001,
      "weighted_center": 88,
      "weighted_right": 3.7,
      "weighted_total": 183.5,
      "seasons_used": [
        "2023",
        "2024",
        "2025"
      ]
    },
    {
      "player_name": "Rick DelGizzi",
      "h2l_percentage": 0.18187001140250852,
      "h2c_percentage": 0.7251995438996579,
      "h2r_percentage": 0.09293044469783353,
      "weighted_left": 31.9,
      "weighted_center": 127.2,
      "weighted_right": 16.3,
      "weighted_total": 175.4,
      "seasons_used": [
        "2023",
        "2024",
        "2025"
      ]
    },
    {
      "player_name": "Jason Lew",
      "h2l_percentage": 0.39526411657559196,
      "h2c_percentage": 0.5452337583485125,
      "h2r_percentage": 0.05950212507589558,
      "weighted_left": 65.1,
      "weighted_center": 89.8,
      "weighted_right": 9.8,
      "weighted_total": 164.7,
      "seasons_used": [
        "2023",
        "2024",
        "2025"
      ]
    },
    {
      "player_name": "Ralph Avallone",
      "h2l_percentage": 0.24865229110512133,
      "h2c_percentage": 0.5579514824797843,
      "h2r_percentage": 0.19339622641509435,
      "weighted_left": 36.900000000000006,
      "weighted_center": 82.8,
      "weighted_right": 28.700000000000003,
      "weighted_total": 148.4,
      "seasons_used": [
        "2023",
        "2024",
        "2025"
      ]
    },
    {
      "player_name": "Andrew Conroy",
      "h2l_percentage": 0.25491624180626365,
      "h2c_percentage": 0.7123088128186453,
      "h2r_percentage": 0.03277494537509104,
      "weighted_left": 35,
      "weighted_center": 97.80000000000001,
      "weighted_right": 4.5,
      "weighted_total": 137.3,
      "seasons_used": [
        "2023",
        "2024",
        "2025"
      ]
    },
    {
      "player_name": "Levi Henninger",
      "h2l_percentage": 0.6798418972332015,
      "h2c_percentage": 0.30434782608695654,
      "h2r_percentage": 0.015810276679841896,
      "weighted_left": 86,
      "weighted_center": 38.5,
      "weighted_right": 2,
      "weighted_total": 126.5,
      "seasons_used": [
        "2023",
        "2024",
        "2025"
      ]
    },
    {
      "player_name": "Deron Green",
      "h2l_percentage": 0.5240594925634295,
      "h2c_percentage": 0.43744531933508307,
      "h2r_percentage": 0.03849518810148731,
      "weighted_left": 59.900000000000006,
      "weighted_center": 50,
      "weighted_right": 4.4,
      "weighted_total": 114.30000000000001,
      "seasons_used": [
        "2023",
        "2024",
        "2025"
      ]
    },
    {
      "player_name": "Temple Houston",
      "h2l_percentage": 0.21926229508196718,
      "h2c_percentage": 0.7233606557377048,
      "h2r_percentage": 0.05737704918032786,
      "weighted_left": 21.4,
      "weighted_center": 70.6,
      "weighted_right": 5.6,
      "weighted_total": 97.60000000000001,
      "seasons_used": [
        "2023",
        "2024",
        "2025"
      ]
    },
    {
      "player_name": "Mike Bedell",
      "h2l_percentage": 0.3693693693693693,
      "h2c_percentage": 0.5990990990990991,
      "h2r_percentage": 0.03153153153153153,
      "weighted_left": 32.8,
      "weighted_center": 53.2,
      "weighted_right": 2.8,
      "weighted_total": 88.80000000000001,
      "seasons_used": [
        "2023",
        "2025"
      ]
    },
    {
      "player_name": "Chris Armelino",
      "h2l_percentage": 0.4750593824228028,
      "h2c_percentage": 0.5249406175771971,
      "h2r_percentage": 0,
      "weighted_left": 40,
      "weighted_center": 44.2,
      "weighted_right": 0,
      "weighted_total": 84.2,
      "seasons_used": [
        "2023",
        "2024",
        "2025"
      ]
    },
    {
      "player_name": "Dave Kaiser",
      "h2l_percentage": 0.32053175775480064,
      "h2c_percentage": 0.5524372230428362,
      "h2r_percentage": 0.12703101920236337,
      "weighted_left": 21.700000000000003,
      "weighted_center": 37.400000000000006,
      "weighted_right": 8.6,
      "weighted_total": 67.7,
      "seasons_used": [
        "2024",
        "2025"
      ]
    },
    {
      "player_name": "Victor Segarra",
      "h2l_percentage": 0.7135593220338984,
      "h2c_percentage": 0.2559322033898305,
      "h2r_percentage": 0.030508474576271188,
      "weighted_left": 42.1,
      "weighted_center": 15.1,
      "weighted_right": 1.8,
      "weighted_total": 59,
      "seasons_used": [
        "2024",
        "2025"
      ]
    },
    {
      "player_name": "Greg Restino",
      "h2l_percentage": 0.5,
      "h2c_percentage": 0.4482758620689655,
      "h2r_percentage": 0.05172413793103448,
      "weighted_left": 26.1,
      "weighted_center": 23.400000000000002,
      "weighted_right": 2.7,
      "weighted_total": 52.2,
      "seasons_used": [
        "2024"
      ]
    },
    {
      "player_name": "John Lew",
      "h2l_percentage": 0.2727272727272727,
      "h2c_percentage": 0.5757575757575758,
      "h2r_percentage": 0.15151515151515152,
      "weighted_left": 9,
      "weighted_center": 19,
      "weighted_right": 5,
      "weighted_total": 33,
      "seasons_used": [
        "2025"
      ]
    }
  ],
  "player_derived_stats": [
    {
      "player_name": "Rick DelGizzi",
      "spot": 1,
      "iso": "0.090",
      "xbh_percentage": 0.12758549882889736,
      "productive_pa_percentage": 0.5946302797286526,
      "out_avoidance": 0.5430909150059019,
      "consistency_score": 1,
      "consistency_games": 6,
      "hit_game_percentage": 1,
      "multi_hit_game_percentage": 0.6666666666666666,
      "xbh_game_percentage": 0.16666666666666666,
      "recent_3_game_games": 3,
      "recent_3_game_pa": 14,
      "recent_3_game_ab": 12,
      "recent_3_game_hits": 6,
      "recent_3_game_avg": 0.5,
      "recent_3_game_obp": 0.5,
      "recent_3_game_slg": 0.5,
      "recent_3_game_ops": 1,
      "profile_confidence": "trusted"
    },
    {
      "player_name": "Jason Lew",
      "spot": 2,
      "iso": "0.122",
      "xbh_percentage": 0.17039146775093097,
      "productive_pa_percentage": 0.5924498277259513,
      "out_avoidance": 0.48631560939532487,
      "consistency_score": 1,
      "consistency_games": 6,
      "hit_game_percentage": 1,
      "multi_hit_game_percentage": 0.5,
      "xbh_game_percentage": 0.3333333333333333,
      "recent_3_game_games": 3,
      "recent_3_game_pa": 13,
      "recent_3_game_ab": 11,
      "recent_3_game_hits": 5,
      "recent_3_game_avg": 0.45454545454545453,
      "recent_3_game_obp": 0.38461538461538464,
      "recent_3_game_slg": 0.5454545454545454,
      "recent_3_game_ops": 0.93006993006993,
      "profile_confidence": "trusted"
    },
    {
      "player_name": "Ralph Avallone",
      "spot": 3,
      "iso": "0.200",
      "xbh_percentage": 0.2603471184630736,
      "productive_pa_percentage": 0.7061169357976115,
      "out_avoidance": 0.6214432318958681,
      "consistency_score": 1,
      "consistency_games": 4,
      "hit_game_percentage": 1,
      "multi_hit_game_percentage": 1,
      "xbh_game_percentage": 0.5,
      "recent_3_game_games": 3,
      "recent_3_game_pa": 13,
      "recent_3_game_ab": 12,
      "recent_3_game_hits": 9,
      "recent_3_game_avg": 0.75,
      "recent_3_game_obp": 0.7857142857142857,
      "recent_3_game_slg": 0.8333333333333334,
      "recent_3_game_ops": 1.619047619047619,
      "profile_confidence": "trusted"
    },
    {
      "player_name": "RJ Leonard",
      "spot": 4,
      "iso": "0.171",
      "xbh_percentage": 0.19534181733077874,
      "productive_pa_percentage": 0.5693676673242675,
      "out_avoidance": 0.4643475455002388,
      "consistency_score": 0.8333333333333334,
      "consistency_games": 6,
      "hit_game_percentage": 0.8333333333333334,
      "multi_hit_game_percentage": 0.6666666666666666,
      "xbh_game_percentage": 0.6666666666666666,
      "recent_3_game_games": 3,
      "recent_3_game_pa": 13,
      "recent_3_game_ab": 12,
      "recent_3_game_hits": 6,
      "recent_3_game_avg": 0.5,
      "recent_3_game_obp": 0.5384615384615384,
      "recent_3_game_slg": 0.75,
      "recent_3_game_ops": 1.2884615384615383,
      "profile_confidence": "trusted"
    },
    {
      "player_name": "Levi Henninger",
      "spot": 5,
      "iso": "0.212",
      "xbh_percentage": 0.40991953422395344,
      "productive_pa_percentage": 0.5619525493460946,
      "out_avoidance": 0.4564934724435525,
      "consistency_score": 0.8333333333333334,
      "consistency_games": 6,
      "hit_game_percentage": 0.8333333333333334,
      "multi_hit_game_percentage": 0.5,
      "xbh_game_percentage": 0.5,
      "recent_3_game_games": 3,
      "recent_3_game_pa": 13,
      "recent_3_game_ab": 12,
      "recent_3_game_hits": 7,
      "recent_3_game_avg": 0.5833333333333334,
      "recent_3_game_obp": 0.6428571428571429,
      "recent_3_game_slg": 1.75,
      "recent_3_game_ops": 2.392857142857143,
      "profile_confidence": "trusted"
    },
    {
      "player_name": "Dave Kaiser",
      "spot": 6,
      "iso": "0.009",
      "xbh_percentage": 0.018386108273748723,
      "productive_pa_percentage": 0.5653080707938606,
      "out_avoidance": 0.4716516119556437,
      "consistency_score": 0.6,
      "consistency_games": 5,
      "hit_game_percentage": 0.6,
      "multi_hit_game_percentage": 0.4,
      "xbh_game_percentage": 0,
      "recent_3_game_games": 3,
      "recent_3_game_pa": 12,
      "recent_3_game_ab": 10,
      "recent_3_game_hits": 6,
      "recent_3_game_avg": 0.6,
      "recent_3_game_obp": 0.6666666666666666,
      "recent_3_game_slg": 0.6,
      "recent_3_game_ops": 1.2666666666666666,
      "profile_confidence": "trusted"
    },
    {
      "player_name": "John Lew",
      "spot": 7,
      "iso": "0.112",
      "xbh_percentage": 0.17336808140977908,
      "productive_pa_percentage": 0.524741081703107,
      "out_avoidance": 0.42117376294591485,
      "consistency_score": 1,
      "consistency_games": 3,
      "hit_game_percentage": 1,
      "multi_hit_game_percentage": 0.3333333333333333,
      "xbh_game_percentage": 0.3333333333333333,
      "recent_3_game_games": 3,
      "recent_3_game_pa": 11,
      "recent_3_game_ab": 11,
      "recent_3_game_hits": 6,
      "recent_3_game_avg": 0.5454545454545454,
      "recent_3_game_obp": 0.5454545454545454,
      "recent_3_game_slg": 0.6363636363636364,
      "recent_3_game_ops": 1.1818181818181817,
      "profile_confidence": "trusted"
    },
    {
      "player_name": "Mike Bedell",
      "spot": 8,
      "iso": "0.086",
      "xbh_percentage": 0.11172731192587962,
      "productive_pa_percentage": 0.539610915495759,
      "out_avoidance": 0.42322069564691644,
      "consistency_score": 1,
      "consistency_games": 7,
      "hit_game_percentage": 1,
      "multi_hit_game_percentage": 0.5714285714285714,
      "xbh_game_percentage": 0.2857142857142857,
      "recent_3_game_games": 3,
      "recent_3_game_pa": 12,
      "recent_3_game_ab": 10,
      "recent_3_game_hits": 5,
      "recent_3_game_avg": 0.5,
      "recent_3_game_obp": 0.5833333333333334,
      "recent_3_game_slg": 1,
      "recent_3_game_ops": 1.5833333333333335,
      "profile_confidence": "trusted"
    },
    {
      "player_name": "Greg Restino",
      "spot": 9,
      "iso": "0.054",
      "xbh_percentage": 0.08669413423070328,
      "productive_pa_percentage": 0.5215909041807757,
      "out_avoidance": 0.44247202566048827,
      "consistency_score": 0.6666666666666666,
      "consistency_games": 3,
      "hit_game_percentage": 0.6666666666666666,
      "multi_hit_game_percentage": 0,
      "xbh_game_percentage": 0,
      "recent_3_game_games": 3,
      "recent_3_game_pa": 11,
      "recent_3_game_ab": 10,
      "recent_3_game_hits": 2,
      "recent_3_game_avg": 0.2,
      "recent_3_game_obp": 0.18181818181818182,
      "recent_3_game_slg": 0.2,
      "recent_3_game_ops": 0.38181818181818183,
      "profile_confidence": "trusted"
    },
    {
      "player_name": "Mark Armelino",
      "spot": 10,
      "iso": "0.024",
      "xbh_percentage": 0.048122619116641285,
      "productive_pa_percentage": 0.5128788274671215,
      "out_avoidance": 0.43826581648152546,
      "consistency_score": 0.6666666666666666,
      "consistency_games": 6,
      "hit_game_percentage": 0.6666666666666666,
      "multi_hit_game_percentage": 0.16666666666666666,
      "xbh_game_percentage": 0,
      "recent_3_game_games": 3,
      "recent_3_game_pa": 12,
      "recent_3_game_ab": 11,
      "recent_3_game_hits": 3,
      "recent_3_game_avg": 0.2727272727272727,
      "recent_3_game_obp": 0.3333333333333333,
      "recent_3_game_slg": 0.2727272727272727,
      "recent_3_game_ops": 0.606060606060606,
      "profile_confidence": "trusted"
    },
    {
      "player_name": "Chris Armelino",
      "spot": 11,
      "iso": "0.055",
      "xbh_percentage": 0.13895558683753276,
      "productive_pa_percentage": 0.5046875844851567,
      "out_avoidance": 0.36475278954907553,
      "consistency_score": 1,
      "consistency_games": 4,
      "hit_game_percentage": 1,
      "multi_hit_game_percentage": 0.5,
      "xbh_game_percentage": 0,
      "recent_3_game_games": 3,
      "recent_3_game_pa": 11,
      "recent_3_game_ab": 11,
      "recent_3_game_hits": 6,
      "recent_3_game_avg": 0.5454545454545454,
      "recent_3_game_obp": 0.6153846153846154,
      "recent_3_game_slg": 0.5454545454545454,
      "recent_3_game_ops": 1.1608391608391608,
      "profile_confidence": "trusted"
    },
    {
      "player_name": "Andrew Conroy",
      "spot": 12,
      "iso": "0.024",
      "xbh_percentage": 0.027203991506871153,
      "productive_pa_percentage": 0.4479568128113683,
      "out_avoidance": 0.32092304944796457,
      "consistency_score": 0.8333333333333334,
      "consistency_games": 6,
      "hit_game_percentage": 0.8333333333333334,
      "multi_hit_game_percentage": 0.5,
      "xbh_game_percentage": 0,
      "recent_3_game_games": 3,
      "recent_3_game_pa": 13,
      "recent_3_game_ab": 13,
      "recent_3_game_hits": 6,
      "recent_3_game_avg": 0.46153846153846156,
      "recent_3_game_obp": 0.46153846153846156,
      "recent_3_game_slg": 0.46153846153846156,
      "recent_3_game_ops": 0.9230769230769231,
      "profile_confidence": "trusted"
    },
    {
      "player_name": "Temple Houston",
      "spot": 13,
      "iso": "0.020",
      "xbh_percentage": 0.050010398004526585,
      "productive_pa_percentage": 0.4429738123700197,
      "out_avoidance": 0.3384191401295146,
      "consistency_score": 0.6,
      "consistency_games": 5,
      "hit_game_percentage": 0.6,
      "multi_hit_game_percentage": 0.4,
      "xbh_game_percentage": 0.2,
      "recent_3_game_games": 3,
      "recent_3_game_pa": 13,
      "recent_3_game_ab": 13,
      "recent_3_game_hits": 7,
      "recent_3_game_avg": 0.5384615384615384,
      "recent_3_game_obp": 0.6,
      "recent_3_game_slg": 0.6153846153846154,
      "recent_3_game_ops": 1.2153846153846155,
      "profile_confidence": "trusted"
    },
    {
      "player_name": "Victor Segarra",
      "spot": 14,
      "iso": "0.000",
      "xbh_percentage": 0,
      "productive_pa_percentage": 0.4571703230679438,
      "out_avoidance": 0.35911697050846286,
      "consistency_score": 1,
      "consistency_games": 1,
      "hit_game_percentage": 1,
      "multi_hit_game_percentage": 1,
      "xbh_game_percentage": 0,
      "recent_3_game_games": 1,
      "recent_3_game_pa": 3,
      "recent_3_game_ab": 3,
      "recent_3_game_hits": 2,
      "recent_3_game_avg": 0.6666666666666666,
      "recent_3_game_obp": 0.6666666666666666,
      "recent_3_game_slg": 0.6666666666666666,
      "recent_3_game_ops": 1.3333333333333333,
      "profile_confidence": "trusted"
    },
    {
      "player_name": "Deron Green",
      "spot": 15,
      "iso": "0.014",
      "xbh_percentage": 0.03786865604797367,
      "productive_pa_percentage": 0.4398964488153399,
      "out_avoidance": 0.33679911674479196,
      "consistency_score": 0.5,
      "consistency_games": 4,
      "hit_game_percentage": 0.5,
      "multi_hit_game_percentage": 0.5,
      "xbh_game_percentage": 0,
      "recent_3_game_games": 3,
      "recent_3_game_pa": 12,
      "recent_3_game_ab": 11,
      "recent_3_game_hits": 5,
      "recent_3_game_avg": 0.45454545454545453,
      "recent_3_game_obp": 0.5384615384615384,
      "recent_3_game_slg": 0.45454545454545453,
      "recent_3_game_ops": 0.9930069930069929,
      "profile_confidence": "trusted"
    }
  ],
  "best_full_order_if_everyone_shows": [
    {
      "spot": 1,
      "lineup_role": "Leadoff",
      "player_name": "Rick DelGizzi",
      "matched": "yes",
      "league_bat_score_rank": 40,
      "league_bat_score_rank_label": "40th of 180 ranked players",
      "offense_index": 0.5665673081978685,
      "projected_offense_index": 0.5683268701043005,
      "trend_adjustment": "0.0018",
      "profile_confidence": "trusted",
      "current_season_sample": 26,
      "previous_season_sample": 61,
      "recent_sample": 87,
      "h2l_percentage": 0.18187001140250852,
      "h2c_percentage": 0.7251995438996579,
      "h2r_percentage": 0.09293044469783353,
      "direction_seasons_used": [
        "2023",
        "2024",
        "2025"
      ],
      "weighted_h2l": 31.9,
      "weighted_h2c": 127.2,
      "weighted_h2r": 16.3,
      "weighted_direction_total": 175.4,
      "line_out_percentage": 0.040001256913021616,
      "fly_out_percentage": 0.7684766214177979,
      "ground_out_percentage": 0.1915221216691805,
      "weighted_line_outs": 1.47,
      "weighted_fly_outs": 28.17,
      "weighted_ground_outs": 7.02,
      "avg": "0.546",
      "obp": "0.565",
      "slg": "0.636",
      "ops": "0.978",
      "iso": "0.090",
      "xbh_percentage": 0.12758549882889736,
      "productive_pa_percentage": 0.5946302797286526,
      "out_avoidance": 0.5430909150059019,
      "consistency_score": 1,
      "consistency_games": 6,
      "hit_game_percentage": 1,
      "multi_hit_game_percentage": 0.6666666666666666,
      "xbh_game_percentage": 0.16666666666666666,
      "recent_3_game_games": 3,
      "recent_3_game_pa": 14,
      "recent_3_game_ab": 12,
      "recent_3_game_hits": 6,
      "recent_3_game_avg": 0.5,
      "recent_3_game_obp": 0.5,
      "recent_3_game_slg": 0.5,
      "recent_3_game_ops": 1,
      "notes": ""
    },
    {
      "spot": 2,
      "lineup_role": "2-hole",
      "player_name": "Jason Lew",
      "matched": "yes",
      "league_bat_score_rank": 32,
      "league_bat_score_rank_label": "32nd of 180 ranked players",
      "offense_index": 0.5644118240600235,
      "projected_offense_index": 0.5749622791892846,
      "trend_adjustment": "0.0106",
      "profile_confidence": "trusted",
      "current_season_sample": 24,
      "previous_season_sample": 57,
      "recent_sample": 81,
      "h2l_percentage": 0.39526411657559196,
      "h2c_percentage": 0.5452337583485125,
      "h2r_percentage": 0.05950212507589558,
      "direction_seasons_used": [
        "2023",
        "2024",
        "2025"
      ],
      "weighted_h2l": 65.1,
      "weighted_h2c": 89.8,
      "weighted_h2r": 9.8,
      "weighted_direction_total": 164.7,
      "line_out_percentage": 0.040679633694089154,
      "fly_out_percentage": 0.7514568985090441,
      "ground_out_percentage": 0.20786346779686674,
      "weighted_line_outs": 1.24,
      "weighted_fly_outs": 22.88,
      "weighted_ground_outs": 6.33,
      "avg": "0.544",
      "obp": "0.539",
      "slg": "0.666",
      "ops": "0.980",
      "iso": "0.122",
      "xbh_percentage": 0.17039146775093097,
      "productive_pa_percentage": 0.5924498277259513,
      "out_avoidance": 0.48631560939532487,
      "consistency_score": 1,
      "consistency_games": 6,
      "hit_game_percentage": 1,
      "multi_hit_game_percentage": 0.5,
      "xbh_game_percentage": 0.3333333333333333,
      "recent_3_game_games": 3,
      "recent_3_game_pa": 13,
      "recent_3_game_ab": 11,
      "recent_3_game_hits": 5,
      "recent_3_game_avg": 0.45454545454545453,
      "recent_3_game_obp": 0.38461538461538464,
      "recent_3_game_slg": 0.5454545454545454,
      "recent_3_game_ops": 0.93006993006993,
      "notes": ""
    },
    {
      "spot": 3,
      "lineup_role": "3-hole",
      "player_name": "Ralph Avallone",
      "matched": "yes",
      "league_bat_score_rank": 4,
      "league_bat_score_rank_label": "4th of 180 ranked players",
      "offense_index": 0.644516751406279,
      "projected_offense_index": 0.6590827277594159,
      "trend_adjustment": "0.0146",
      "profile_confidence": "trusted",
      "current_season_sample": 16,
      "previous_season_sample": 43,
      "recent_sample": 59,
      "h2l_percentage": 0.24865229110512133,
      "h2c_percentage": 0.5579514824797843,
      "h2r_percentage": 0.19339622641509435,
      "direction_seasons_used": [
        "2023",
        "2024",
        "2025"
      ],
      "weighted_h2l": 36.900000000000006,
      "weighted_h2c": 82.8,
      "weighted_h2r": 28.700000000000003,
      "weighted_direction_total": 148.4,
      "line_out_percentage": 0.054751052904863554,
      "fly_out_percentage": 0.561703109675186,
      "ground_out_percentage": 0.38354583741995035,
      "weighted_line_outs": 1.09,
      "weighted_fly_outs": 11.22,
      "weighted_ground_outs": 7.66,
      "avg": "0.641",
      "obp": "0.662",
      "slg": "0.841",
      "ops": "1.246",
      "iso": "0.200",
      "xbh_percentage": 0.2603471184630736,
      "productive_pa_percentage": 0.7061169357976115,
      "out_avoidance": 0.6214432318958681,
      "consistency_score": 1,
      "consistency_games": 4,
      "hit_game_percentage": 1,
      "multi_hit_game_percentage": 1,
      "xbh_game_percentage": 0.5,
      "recent_3_game_games": 3,
      "recent_3_game_pa": 13,
      "recent_3_game_ab": 12,
      "recent_3_game_hits": 9,
      "recent_3_game_avg": 0.75,
      "recent_3_game_obp": 0.7857142857142857,
      "recent_3_game_slg": 0.8333333333333334,
      "recent_3_game_ops": 1.619047619047619,
      "notes": ""
    },
    {
      "spot": 4,
      "lineup_role": "Cleanup",
      "player_name": "RJ Leonard",
      "matched": "yes",
      "league_bat_score_rank": 59,
      "league_bat_score_rank_label": "59th of 180 ranked players",
      "offense_index": 0.5640656050135564,
      "projected_offense_index": 0.5497265862369334,
      "trend_adjustment": "-0.0143",
      "profile_confidence": "trusted",
      "current_season_sample": 23,
      "previous_season_sample": 69,
      "recent_sample": 92,
      "h2l_percentage": 0.6231647634584013,
      "h2c_percentage": 0.3681348558999456,
      "h2r_percentage": 0.008700380641653073,
      "direction_seasons_used": [
        "2023",
        "2024",
        "2025"
      ],
      "weighted_h2l": 114.60000000000001,
      "weighted_h2c": 67.7,
      "weighted_h2r": 1.6,
      "weighted_direction_total": 183.9,
      "line_out_percentage": 0.02142171647929806,
      "fly_out_percentage": 0.6360364683301344,
      "ground_out_percentage": 0.34254181519056764,
      "weighted_line_outs": 0.72,
      "weighted_fly_outs": 21.38,
      "weighted_ground_outs": 11.51,
      "avg": "0.520",
      "obp": "0.525",
      "slg": "0.692",
      "ops": "1.007",
      "iso": "0.171",
      "xbh_percentage": 0.19534181733077874,
      "productive_pa_percentage": 0.5693676673242675,
      "out_avoidance": 0.4643475455002388,
      "consistency_score": 0.8333333333333334,
      "consistency_games": 6,
      "hit_game_percentage": 0.8333333333333334,
      "multi_hit_game_percentage": 0.6666666666666666,
      "xbh_game_percentage": 0.6666666666666666,
      "recent_3_game_games": 3,
      "recent_3_game_pa": 13,
      "recent_3_game_ab": 12,
      "recent_3_game_hits": 6,
      "recent_3_game_avg": 0.5,
      "recent_3_game_obp": 0.5384615384615384,
      "recent_3_game_slg": 0.75,
      "recent_3_game_ops": 1.2884615384615383,
      "notes": ""
    },
    {
      "spot": 5,
      "lineup_role": "5-hole",
      "player_name": "Levi Henninger",
      "matched": "yes",
      "league_bat_score_rank": 112,
      "league_bat_score_rank_label": "112th of 180 ranked players",
      "offense_index": 0.5362926402471535,
      "projected_offense_index": 0.4962926402471535,
      "trend_adjustment": "-0.0400",
      "profile_confidence": "trusted",
      "current_season_sample": 23,
      "previous_season_sample": 40,
      "recent_sample": 63,
      "h2l_percentage": 0.6798418972332015,
      "h2c_percentage": 0.30434782608695654,
      "h2r_percentage": 0.015810276679841896,
      "direction_seasons_used": [
        "2023",
        "2024",
        "2025"
      ],
      "weighted_h2l": 86,
      "weighted_h2c": 38.5,
      "weighted_h2r": 2,
      "weighted_direction_total": 126.5,
      "line_out_percentage": 0.026308035526371176,
      "fly_out_percentage": 0.7896619943595572,
      "ground_out_percentage": 0.18402997011407163,
      "weighted_line_outs": 0.72,
      "weighted_fly_outs": 21.61,
      "weighted_ground_outs": 5.04,
      "avg": "0.477",
      "obp": "0.505",
      "slg": "0.589",
      "ops": "0.982",
      "iso": "0.212",
      "xbh_percentage": 0.40991953422395344,
      "productive_pa_percentage": 0.5619525493460946,
      "out_avoidance": 0.4564934724435525,
      "consistency_score": 0.8333333333333334,
      "consistency_games": 6,
      "hit_game_percentage": 0.8333333333333334,
      "multi_hit_game_percentage": 0.5,
      "xbh_game_percentage": 0.5,
      "recent_3_game_games": 3,
      "recent_3_game_pa": 13,
      "recent_3_game_ab": 12,
      "recent_3_game_hits": 7,
      "recent_3_game_avg": 0.5833333333333334,
      "recent_3_game_obp": 0.6428571428571429,
      "recent_3_game_slg": 1.75,
      "recent_3_game_ops": 2.392857142857143,
      "notes": ""
    },
    {
      "spot": 6,
      "lineup_role": "Middle order",
      "player_name": "Dave Kaiser",
      "matched": "yes",
      "league_bat_score_rank": 102,
      "league_bat_score_rank_label": "102nd of 180 ranked players",
      "offense_index": 0.5138649136968968,
      "projected_offense_index": 0.506383864238423,
      "trend_adjustment": "-0.0075",
      "profile_confidence": "trusted",
      "current_season_sample": 18,
      "previous_season_sample": 28,
      "recent_sample": 46,
      "h2l_percentage": 0.32053175775480064,
      "h2c_percentage": 0.5524372230428362,
      "h2r_percentage": 0.12703101920236337,
      "direction_seasons_used": [
        "2024",
        "2025"
      ],
      "weighted_h2l": 21.700000000000003,
      "weighted_h2c": 37.400000000000006,
      "weighted_h2r": 8.6,
      "weighted_direction_total": 67.7,
      "line_out_percentage": 0.06976744186046512,
      "fly_out_percentage": 0.4786821705426357,
      "ground_out_percentage": 0.45155038759689925,
      "weighted_line_outs": 1.04,
      "weighted_fly_outs": 7.11,
      "weighted_ground_outs": 6.71,
      "avg": "0.468",
      "obp": "0.540",
      "slg": "0.478",
      "ops": "0.731",
      "iso": "0.009",
      "xbh_percentage": 0.018386108273748723,
      "productive_pa_percentage": 0.5653080707938606,
      "out_avoidance": 0.4716516119556437,
      "consistency_score": 0.6,
      "consistency_games": 5,
      "hit_game_percentage": 0.6,
      "multi_hit_game_percentage": 0.4,
      "xbh_game_percentage": 0,
      "recent_3_game_games": 3,
      "recent_3_game_pa": 12,
      "recent_3_game_ab": 10,
      "recent_3_game_hits": 6,
      "recent_3_game_avg": 0.6,
      "recent_3_game_obp": 0.6666666666666666,
      "recent_3_game_slg": 0.6,
      "recent_3_game_ops": 1.2666666666666666,
      "notes": ""
    },
    {
      "spot": 7,
      "lineup_role": "Middle order",
      "player_name": "John Lew",
      "matched": "yes",
      "league_bat_score_rank": 66,
      "league_bat_score_rank_label": "66th of 180 ranked players",
      "offense_index": 0.541340551263238,
      "projected_offense_index": 0.5398549832985939,
      "trend_adjustment": "-0.0015",
      "profile_confidence": "trusted",
      "current_season_sample": 11,
      "previous_season_sample": 33,
      "recent_sample": 44,
      "h2l_percentage": 0.2727272727272727,
      "h2c_percentage": 0.5757575757575758,
      "h2r_percentage": 0.15151515151515152,
      "direction_seasons_used": [
        "2025"
      ],
      "weighted_h2l": 9,
      "weighted_h2c": 19,
      "weighted_h2r": 5,
      "weighted_direction_total": 33,
      "line_out_percentage": 0,
      "fly_out_percentage": 0.3333333333333333,
      "ground_out_percentage": 0.6666666666666666,
      "weighted_line_outs": 0,
      "weighted_fly_outs": 2.16,
      "weighted_ground_outs": 4.32,
      "avg": "0.524",
      "obp": "0.524",
      "slg": "0.636",
      "ops": "0.787",
      "iso": "0.112",
      "xbh_percentage": 0.17336808140977908,
      "productive_pa_percentage": 0.524741081703107,
      "out_avoidance": 0.42117376294591485,
      "consistency_score": 1,
      "consistency_games": 3,
      "hit_game_percentage": 1,
      "multi_hit_game_percentage": 0.3333333333333333,
      "xbh_game_percentage": 0.3333333333333333,
      "recent_3_game_games": 3,
      "recent_3_game_pa": 11,
      "recent_3_game_ab": 11,
      "recent_3_game_hits": 6,
      "recent_3_game_avg": 0.5454545454545454,
      "recent_3_game_obp": 0.5454545454545454,
      "recent_3_game_slg": 0.6363636363636364,
      "recent_3_game_ops": 1.1818181818181817,
      "notes": ""
    },
    {
      "spot": 8,
      "lineup_role": "Middle order",
      "player_name": "Mike Bedell",
      "matched": "yes",
      "league_bat_score_rank": 75,
      "league_bat_score_rank_label": "75th of 180 ranked players",
      "offense_index": 0.514213181241958,
      "projected_offense_index": 0.5288657632926238,
      "trend_adjustment": "0.0147",
      "profile_confidence": "trusted",
      "current_season_sample": 26,
      "previous_season_sample": 44,
      "recent_sample": 70,
      "h2l_percentage": 0.3693693693693693,
      "h2c_percentage": 0.5990990990990991,
      "h2r_percentage": 0.03153153153153153,
      "direction_seasons_used": [
        "2023",
        "2025"
      ],
      "weighted_h2l": 32.8,
      "weighted_h2c": 53.2,
      "weighted_h2r": 2.8,
      "weighted_direction_total": 88.80000000000001,
      "line_out_percentage": 0.03136133273119574,
      "fly_out_percentage": 0.5748908625620953,
      "ground_out_percentage": 0.3937478047067088,
      "weighted_line_outs": 0.72,
      "weighted_fly_outs": 13.2,
      "weighted_ground_outs": 9.04,
      "avg": "0.468",
      "obp": "0.505",
      "slg": "0.554",
      "ops": "0.661",
      "iso": "0.086",
      "xbh_percentage": 0.11172731192587962,
      "productive_pa_percentage": 0.539610915495759,
      "out_avoidance": 0.42322069564691644,
      "consistency_score": 1,
      "consistency_games": 7,
      "hit_game_percentage": 1,
      "multi_hit_game_percentage": 0.5714285714285714,
      "xbh_game_percentage": 0.2857142857142857,
      "recent_3_game_games": 3,
      "recent_3_game_pa": 12,
      "recent_3_game_ab": 10,
      "recent_3_game_hits": 5,
      "recent_3_game_avg": 0.5,
      "recent_3_game_obp": 0.5833333333333334,
      "recent_3_game_slg": 1,
      "recent_3_game_ops": 1.5833333333333335,
      "notes": ""
    },
    {
      "spot": 9,
      "lineup_role": "Middle order",
      "player_name": "Greg Restino",
      "matched": "yes",
      "league_bat_score_rank": 115,
      "league_bat_score_rank_label": "115th of 180 ranked players",
      "offense_index": 0.5187093998655505,
      "projected_offense_index": 0.4930930001258809,
      "trend_adjustment": "-0.0256",
      "profile_confidence": "trusted",
      "current_season_sample": 11,
      "previous_season_sample": 33,
      "recent_sample": 44,
      "h2l_percentage": 0.5,
      "h2c_percentage": 0.4482758620689655,
      "h2r_percentage": 0.05172413793103448,
      "direction_seasons_used": [
        "2024"
      ],
      "weighted_h2l": 26.1,
      "weighted_h2c": 23.400000000000002,
      "weighted_h2r": 2.7,
      "weighted_direction_total": 52.2,
      "line_out_percentage": 0,
      "fly_out_percentage": 0.782051282051282,
      "ground_out_percentage": 0.21794871794871795,
      "weighted_line_outs": 0,
      "weighted_fly_outs": 14.05,
      "weighted_ground_outs": 3.92,
      "avg": "0.477",
      "obp": "0.464",
      "slg": "0.531",
      "ops": "0.995",
      "iso": "0.054",
      "xbh_percentage": 0.08669413423070328,
      "productive_pa_percentage": 0.5215909041807757,
      "out_avoidance": 0.44247202566048827,
      "consistency_score": 0.6666666666666666,
      "consistency_games": 3,
      "hit_game_percentage": 0.6666666666666666,
      "multi_hit_game_percentage": 0,
      "xbh_game_percentage": 0,
      "recent_3_game_games": 3,
      "recent_3_game_pa": 11,
      "recent_3_game_ab": 10,
      "recent_3_game_hits": 2,
      "recent_3_game_avg": 0.2,
      "recent_3_game_obp": 0.18181818181818182,
      "recent_3_game_slg": 0.2,
      "recent_3_game_ops": 0.38181818181818183,
      "notes": ""
    },
    {
      "spot": 10,
      "lineup_role": "Middle order",
      "player_name": "Mark Armelino",
      "matched": "yes",
      "league_bat_score_rank": 130,
      "league_bat_score_rank_label": "130th of 180 ranked players",
      "offense_index": 0.501550698431637,
      "projected_offense_index": 0.4786996306563103,
      "trend_adjustment": "-0.0229",
      "profile_confidence": "trusted",
      "current_season_sample": 22,
      "previous_season_sample": 54,
      "recent_sample": 76,
      "h2l_percentage": 0.5002724795640328,
      "h2c_percentage": 0.47956403269754766,
      "h2r_percentage": 0.020163487738419618,
      "direction_seasons_used": [
        "2023",
        "2024",
        "2025"
      ],
      "weighted_h2l": 91.80000000000001,
      "weighted_h2c": 88,
      "weighted_h2r": 3.7,
      "weighted_direction_total": 183.5,
      "line_out_percentage": 0.07687198067632849,
      "fly_out_percentage": 0.4705314009661835,
      "ground_out_percentage": 0.45259661835748793,
      "weighted_line_outs": 2.93,
      "weighted_fly_outs": 17.95,
      "weighted_ground_outs": 17.27,
      "avg": "0.465",
      "obp": "0.476",
      "slg": "0.489",
      "ops": "0.965",
      "iso": "0.024",
      "xbh_percentage": 0.048122619116641285,
      "productive_pa_percentage": 0.5128788274671215,
      "out_avoidance": 0.43826581648152546,
      "consistency_score": 0.6666666666666666,
      "consistency_games": 6,
      "hit_game_percentage": 0.6666666666666666,
      "multi_hit_game_percentage": 0.16666666666666666,
      "xbh_game_percentage": 0,
      "recent_3_game_games": 3,
      "recent_3_game_pa": 12,
      "recent_3_game_ab": 11,
      "recent_3_game_hits": 3,
      "recent_3_game_avg": 0.2727272727272727,
      "recent_3_game_obp": 0.3333333333333333,
      "recent_3_game_slg": 0.2727272727272727,
      "recent_3_game_ops": 0.606060606060606,
      "notes": ""
    },
    {
      "spot": 11,
      "lineup_role": "Bottom order",
      "player_name": "Chris Armelino",
      "matched": "yes",
      "league_bat_score_rank": 124,
      "league_bat_score_rank_label": "124th of 180 ranked players",
      "offense_index": 0.4670937860286004,
      "projected_offense_index": 0.48764990126900565,
      "trend_adjustment": "0.0206",
      "profile_confidence": "trusted",
      "current_season_sample": 14,
      "previous_season_sample": 27,
      "recent_sample": 41,
      "h2l_percentage": 0.4750593824228028,
      "h2c_percentage": 0.5249406175771971,
      "h2r_percentage": 0,
      "direction_seasons_used": [
        "2023",
        "2024",
        "2025"
      ],
      "weighted_h2l": 40,
      "weighted_h2c": 44.2,
      "weighted_h2r": 0,
      "weighted_direction_total": 84.2,
      "line_out_percentage": 0.05520218082689686,
      "fly_out_percentage": 0.7220581553839164,
      "ground_out_percentage": 0.2227396637891867,
      "weighted_line_outs": 1.12,
      "weighted_fly_outs": 14.65,
      "weighted_ground_outs": 4.52,
      "avg": "0.382",
      "obp": "0.438",
      "slg": "0.437",
      "ops": "0.652",
      "iso": "0.055",
      "xbh_percentage": 0.13895558683753276,
      "productive_pa_percentage": 0.5046875844851567,
      "out_avoidance": 0.36475278954907553,
      "consistency_score": 1,
      "consistency_games": 4,
      "hit_game_percentage": 1,
      "multi_hit_game_percentage": 0.5,
      "xbh_game_percentage": 0,
      "recent_3_game_games": 3,
      "recent_3_game_pa": 11,
      "recent_3_game_ab": 11,
      "recent_3_game_hits": 6,
      "recent_3_game_avg": 0.5454545454545454,
      "recent_3_game_obp": 0.6153846153846154,
      "recent_3_game_slg": 0.5454545454545454,
      "recent_3_game_ops": 1.1608391608391608,
      "notes": ""
    },
    {
      "spot": 12,
      "lineup_role": "Bottom order",
      "player_name": "Andrew Conroy",
      "matched": "yes",
      "league_bat_score_rank": 116,
      "league_bat_score_rank_label": "116th of 180 ranked players",
      "offense_index": 0.45433632832288967,
      "projected_offense_index": 0.49276457573504695,
      "trend_adjustment": "0.0384",
      "profile_confidence": "trusted",
      "current_season_sample": 25,
      "previous_season_sample": 45,
      "recent_sample": 70,
      "h2l_percentage": 0.25491624180626365,
      "h2c_percentage": 0.7123088128186453,
      "h2r_percentage": 0.03277494537509104,
      "direction_seasons_used": [
        "2023",
        "2024",
        "2025"
      ],
      "weighted_h2l": 35,
      "weighted_h2c": 97.80000000000001,
      "weighted_h2r": 4.5,
      "weighted_direction_total": 137.3,
      "line_out_percentage": 0.11672910796668422,
      "fly_out_percentage": 0.513484224540979,
      "ground_out_percentage": 0.3697866674923367,
      "weighted_line_outs": 4.34,
      "weighted_fly_outs": 19.1,
      "weighted_ground_outs": 13.76,
      "avg": "0.405",
      "obp": "0.413",
      "slg": "0.429",
      "ops": "0.842",
      "iso": "0.024",
      "xbh_percentage": 0.027203991506871153,
      "productive_pa_percentage": 0.4479568128113683,
      "out_avoidance": 0.32092304944796457,
      "consistency_score": 0.8333333333333334,
      "consistency_games": 6,
      "hit_game_percentage": 0.8333333333333334,
      "multi_hit_game_percentage": 0.5,
      "xbh_game_percentage": 0,
      "recent_3_game_games": 3,
      "recent_3_game_pa": 13,
      "recent_3_game_ab": 13,
      "recent_3_game_hits": 6,
      "recent_3_game_avg": 0.46153846153846156,
      "recent_3_game_obp": 0.46153846153846156,
      "recent_3_game_slg": 0.46153846153846156,
      "recent_3_game_ops": 0.9230769230769231,
      "notes": ""
    },
    {
      "spot": 13,
      "lineup_role": "Bottom order",
      "player_name": "Temple Houston",
      "matched": "yes",
      "league_bat_score_rank": 119,
      "league_bat_score_rank_label": "119th of 180 ranked players",
      "offense_index": 0.45392373050061624,
      "projected_offense_index": 0.4902454865368965,
      "trend_adjustment": "0.0363",
      "profile_confidence": "trusted",
      "current_season_sample": 19,
      "previous_season_sample": 38,
      "recent_sample": 57,
      "h2l_percentage": 0.21926229508196718,
      "h2c_percentage": 0.7233606557377048,
      "h2r_percentage": 0.05737704918032786,
      "direction_seasons_used": [
        "2023",
        "2024",
        "2025"
      ],
      "weighted_h2l": 21.4,
      "weighted_h2c": 70.6,
      "weighted_h2r": 5.6,
      "weighted_direction_total": 97.60000000000001,
      "line_out_percentage": 0.0576232760249386,
      "fly_out_percentage": 0.6751558662384282,
      "ground_out_percentage": 0.2672208577366333,
      "weighted_line_outs": 1.76,
      "weighted_fly_outs": 20.58,
      "weighted_ground_outs": 8.15,
      "avg": "0.385",
      "obp": "0.412",
      "slg": "0.404",
      "ops": "0.816",
      "iso": "0.020",
      "xbh_percentage": 0.050010398004526585,
      "productive_pa_percentage": 0.4429738123700197,
      "out_avoidance": 0.3384191401295146,
      "consistency_score": 0.6,
      "consistency_games": 5,
      "hit_game_percentage": 0.6,
      "multi_hit_game_percentage": 0.4,
      "xbh_game_percentage": 0.2,
      "recent_3_game_games": 3,
      "recent_3_game_pa": 13,
      "recent_3_game_ab": 13,
      "recent_3_game_hits": 7,
      "recent_3_game_avg": 0.5384615384615384,
      "recent_3_game_obp": 0.6,
      "recent_3_game_slg": 0.6153846153846154,
      "recent_3_game_ops": 1.2153846153846155,
      "notes": ""
    },
    {
      "spot": 14,
      "lineup_role": "Bottom order",
      "player_name": "Victor Segarra",
      "matched": "yes",
      "league_bat_score_rank": 156,
      "league_bat_score_rank_label": "156th of 180 ranked players",
      "offense_index": 0.43858231577680223,
      "projected_offense_index": 0.4445751072761402,
      "trend_adjustment": "0.0060",
      "profile_confidence": "trusted",
      "current_season_sample": 3,
      "previous_season_sample": 26,
      "recent_sample": 29,
      "h2l_percentage": 0.7135593220338984,
      "h2c_percentage": 0.2559322033898305,
      "h2r_percentage": 0.030508474576271188,
      "direction_seasons_used": [
        "2024",
        "2025"
      ],
      "weighted_h2l": 42.1,
      "weighted_h2c": 15.1,
      "weighted_h2r": 1.8,
      "weighted_direction_total": 59,
      "line_out_percentage": 0.03665987780040733,
      "fly_out_percentage": 0.429735234215886,
      "ground_out_percentage": 0.5336048879837068,
      "weighted_line_outs": 0.52,
      "weighted_fly_outs": 6.08,
      "weighted_ground_outs": 7.55,
      "avg": "0.360",
      "obp": "0.413",
      "slg": "0.360",
      "ops": "0.687",
      "iso": "0.000",
      "xbh_percentage": 0,
      "productive_pa_percentage": 0.4571703230679438,
      "out_avoidance": 0.35911697050846286,
      "consistency_score": 1,
      "consistency_games": 1,
      "hit_game_percentage": 1,
      "multi_hit_game_percentage": 1,
      "xbh_game_percentage": 0,
      "recent_3_game_games": 1,
      "recent_3_game_pa": 3,
      "recent_3_game_ab": 3,
      "recent_3_game_hits": 2,
      "recent_3_game_avg": 0.6666666666666666,
      "recent_3_game_obp": 0.6666666666666666,
      "recent_3_game_slg": 0.6666666666666666,
      "recent_3_game_ops": 1.3333333333333333,
      "notes": ""
    },
    {
      "spot": 15,
      "lineup_role": "Bottom order",
      "player_name": "Deron Green",
      "matched": "yes",
      "league_bat_score_rank": 144,
      "league_bat_score_rank_label": "144th of 180 ranked players",
      "offense_index": 0.44489469470652715,
      "projected_offense_index": 0.4609957858197861,
      "trend_adjustment": "0.0161",
      "profile_confidence": "trusted",
      "current_season_sample": 15,
      "previous_season_sample": 32,
      "recent_sample": 47,
      "h2l_percentage": 0.5240594925634295,
      "h2c_percentage": 0.43744531933508307,
      "h2r_percentage": 0.03849518810148731,
      "direction_seasons_used": [
        "2023",
        "2024",
        "2025"
      ],
      "weighted_h2l": 59.900000000000006,
      "weighted_h2c": 50,
      "weighted_h2r": 4.4,
      "weighted_direction_total": 114.30000000000001,
      "line_out_percentage": 0.05852109481324663,
      "fly_out_percentage": 0.6695523967941933,
      "ground_out_percentage": 0.27192650839256005,
      "weighted_line_outs": 1.78,
      "weighted_fly_outs": 20.4,
      "weighted_ground_outs": 8.29,
      "avg": "0.374",
      "obp": "0.404",
      "slg": "0.388",
      "ops": "0.792",
      "iso": "0.014",
      "xbh_percentage": 0.03786865604797367,
      "productive_pa_percentage": 0.4398964488153399,
      "out_avoidance": 0.33679911674479196,
      "consistency_score": 0.5,
      "consistency_games": 4,
      "hit_game_percentage": 0.5,
      "multi_hit_game_percentage": 0.5,
      "xbh_game_percentage": 0,
      "recent_3_game_games": 3,
      "recent_3_game_pa": 12,
      "recent_3_game_ab": 11,
      "recent_3_game_hits": 5,
      "recent_3_game_avg": 0.45454545454545453,
      "recent_3_game_obp": 0.5384615384615384,
      "recent_3_game_slg": 0.45454545454545453,
      "recent_3_game_ops": 0.9930069930069929,
      "notes": ""
    }
  ],
  "top_5_must_have_players": [
    {
      "player_name": "Ralph Avallone",
      "run_swing": 1.49,
      "win_probability_swing": 0.0801
    },
    {
      "player_name": "Rick DelGizzi",
      "run_swing": 0.81,
      "win_probability_swing": 0.0427
    },
    {
      "player_name": "Levi Henninger",
      "run_swing": 0.8,
      "win_probability_swing": 0.0424
    },
    {
      "player_name": "RJ Leonard",
      "run_swing": 0.76,
      "win_probability_swing": 0.0404
    },
    {
      "player_name": "Jason Lew",
      "run_swing": 0.73,
      "win_probability_swing": 0.0385
    }
  ],
  "lowest_penalty_absences": [
    {
      "player_name": "Temple Houston",
      "run_swing": 0,
      "win_probability_swing": 0
    },
    {
      "player_name": "Mark Armelino",
      "run_swing": 0,
      "win_probability_swing": 0
    },
    {
      "player_name": "Andrew Conroy",
      "run_swing": 0,
      "win_probability_swing": 0
    },
    {
      "player_name": "Deron Green",
      "run_swing": 0,
      "win_probability_swing": 0
    },
    {
      "player_name": "Chris Armelino",
      "run_swing": 0,
      "win_probability_swing": 0
    }
  ],
  "rookies_or_unmatched": []
}
